pyfedic_cython/__init__.py
pyfedic_cython/mesh.pyx
pyfedic_cython/spfast.pyx
pyfedic_cython/mesh.c
pyfedic_cython/mesh.cpython-39-x86_64-linux-gnu.so
pyfedic_cython/spfast.c
pyfedic_cython/spfast.cpython-39-x86_64-linux-gnu.so
pyfedic_cython-25.9.2.dist-info/METADATA
pyfedic_cython-25.9.2.dist-info/WHEEL
pyfedic_cython-25.9.2.dist-info/RECORD
