Metadata-Version: 2.3
Name: pyfedic_cython
Version: 25.9.2
Summary: Digital Image (2D/3D) Correlation Software - CYTHON module
License: CECILL-2.1
Author: Joël Lachambre
Author-email: joel.lachambre@cnrs.fr
Requires-Python: >=3.9,<3.13
Classifier: Intended Audience :: Developers
Classifier: Intended Audience :: Science/Research
Classifier: License :: OSI Approved :: CEA CNRS Inria Logiciel Libre License, version 2.1 (CeCILL-2.1)
Classifier: Operating System :: OS Independent
Classifier: Programming Language :: Python :: 3
Classifier: Programming Language :: Python :: 3.9
Classifier: Programming Language :: Python :: 3.10
Classifier: Programming Language :: Python :: 3.11
Classifier: Programming Language :: Python :: 3.12
Classifier: Topic :: Scientific/Engineering
Classifier: Topic :: Software Development :: Libraries :: Python Modules
Project-URL: Documentation, https://sourcesup.renater.fr/www/pyfedic/html
Project-URL: Homepage, https://sourcesup.renater.fr/www/pyfedic/
